shuidi_data/__init__.py
shuidi_data/api_tool.py
shuidi_data/server.py
shuidi_data_mcp_server-0.1.0.dist-info/METADATA
shuidi_data_mcp_server-0.1.0.dist-info/WHEEL
shuidi_data_mcp_server-0.1.0.dist-info/entry_points.txt
shuidi_data_mcp_server-0.1.0.dist-info/top_level.txt
shuidi_data_mcp_server-0.1.0.dist-info/RECORD
