Metadata-Version: 2.4
Name: shuidi-data-mcp-server
Version: 0.1.0
Summary: Add your description here
Requires-Python: >=3.13
Requires-Dist: loguru>=0.7.3
Requires-Dist: mcp[cli]>=1.6.0
